MANIFEST.in
README.txt
setup.cfg
setup.py
XStatic_AbrilFatFace.egg-info/PKG-INFO
XStatic_AbrilFatFace.egg-info/SOURCES.txt
XStatic_AbrilFatFace.egg-info/dependency_links.txt
XStatic_AbrilFatFace.egg-info/namespace_packages.txt
XStatic_AbrilFatFace.egg-info/not-zip-safe
XStatic_AbrilFatFace.egg-info/top_level.txt
xstatic/__init__.py
xstatic/pkg/__init__.py
xstatic/pkg/abril_fatface/__init__.py
xstatic/pkg/abril_fatface/data/fonts/Regular/abrilfatface-regular.otf
xstatic/pkg/abril_fatface/data/fonts/Regular/abrilfatface-regular.ttf
xstatic/pkg/abril_fatface/data/fonts/Regular/abrilfatface-regular.woff