Metadata-Version: 1.0
Name: XStatic-AbrilFatFace
Version: 0.1.0
Summary: AbrilFatFace 0.1 (XStatic packaging standard)
Home-page: https://www.fontsquirrel.com/fonts/abril-fatface
Author: Serghei Mihai
Author-email: smihai@entrouvert.com
License: (same as AbrilFatFace)
Keywords: abril_fatface xstatic
Platform: any
